README.md
pyproject.toml
setup.cfg
setup.py
see_saw.egg-info/PKG-INFO
see_saw.egg-info/SOURCES.txt
see_saw.egg-info/dependency_links.txt
see_saw.egg-info/entry_points.txt
see_saw.egg-info/not-zip-safe
see_saw.egg-info/requires.txt
see_saw.egg-info/top_level.txt
seesaw/__init__.py
seesaw/config.py
seesaw/entry.py
seesaw/log_factory.py
seesaw/storage.py
seesaw/transforms.py
seesaw/ui_components.py